[
  {
    "id": "chap8-ck1#0",
    "quest": [
      "tragen",
      "~konjugieren~"
    ],
    "answer": [
      "нос_и_ть",
      "я нош_у_",
      "ты н_о_сишь",
      "он / она / оно н_о_сит",
      "мы н_о_сим",
      "вы н_о_сите",
      "они н_о_сят"
    ]
  },
  {
    "id": "chap8-ck1#1",
    "quest": [
      "rot"
    ],
    "answer": [
      "кр_а_сный",
      "кр_а_сная",
      "кр_а_сное",
      "кр_а_сные"
    ]
  },
  {
    "id": "chap8-ck1#2",
    "quest": [
      "gelb"
    ],
    "answer": [
      "жёлтый",
      "жёлтая",
      "жёлтое",
      "жёлтые"
    ]
  },
  {
    "id": "chap8-ck1#3",
    "quest": [
      "grün"
    ],
    "answer": [
      "зелёный",
      "зелёная",
      "зелёное",
      "зелёные"
    ]
  },
  {
    "id": "chap8-ck1#4",
    "quest": [
      "blau"
    ],
    "answer": [
      "с_и_ний",
      "с_и_няя",
      "с_и_нее",
      "с_и_ние"
    ]
  },
  {
    "id": "chap8-ck1#5",
    "quest": [
      "weiß"
    ],
    "answer": [
      "б_е_лый",
      "б_е_лая",
      "б_е_лое",
      "б_е_лые"
    ]
  },
  {
    "id": "chap8-ck1#6",
    "quest": [
      "schwarz"
    ],
    "answer": [
      "чёрный",
      "чёрная",
      "чёрное",
      "чёрные"
    ]
  },
  {
    "id": "chap8-ck1#7",
    "quest": [
      "braun"
    ],
    "answer": [
      "кор_и_чневый",
      "кор_и_чневая",
      "кор_и_чневое",
      "кор_и_чневые"
    ]
  },
  {
    "id": "chap8-ck1#8",
    "quest": [
      "orange"
    ],
    "answer": [
      "ор_а_нжевый",
      "ор_а_нжевая",
      "ор_а_нжевое",
      "ор_а_нжевые"
    ]
  },
  {
    "id": "chap8-ck1#9",
    "quest": [
      "hier: Lieblings-"
    ],
    "answer": [
      "люб_и_мый",
      "люб_и_мая",
      "люб_и_мое",
      "люб_и_мые"
    ]
  },
  {
    "id": "chap8-ck1#10",
    "quest": [
      "Farbe",
      "Farben"
    ],
    "answer": [
      "цвет",
      "цвет_а_ ~Nom. Pl.~"
    ]
  },
  {
    "id": "chap8-ck1#11",
    "quest": [
      "welcher?",
      "was für ein?"
    ],
    "answer": [
      "как_о_й",
      "как_а_я",
      "как_о_е",
      "как_и_е"
    ]
  },
  {
    "id": "chap8-ck1#12",
    "quest": [
      "dieser",
      "diese",
      "dieses",
      "diese ~(Pl.)~"
    ],
    "answer": [
      "_э_тот",
      "_э_та",
      "_э_то",
      "_э_ти"
    ]
  },
  {
    "id": "chap8-ck1#13",
    "quest": [
      "Jacke",
      "Anorak"
    ],
    "answer": [
      "к_у_ртка"
    ]
  },
  {
    "id": "chap8-ck1#14",
    "quest": [
      "Kleidung"
    ],
    "answer": [
      "од_е_жда"
    ]
  },
  {
    "id": "chap8-ck1#15",
    "quest": [
      "Kostüm",
      "Herrenanzug"
    ],
    "answer": [
      "кост_ю_м"
    ]
  },
  {
    "id": "chap8-ck1#16",
    "quest": [
      "Krawatte"
    ],
    "answer": [
      "г_а_лстук"
    ]
  },
  {
    "id": "chap8-ck1#17",
    "quest": [
      "Pullover"
    ],
    "answer": [
      "пул_о_вер"
    ]
  },
  {
    "id": "chap8-ck1#18",
    "quest": [
      "~Pl.~ Brille"
    ],
    "answer": [
      "очк_и_"
    ]
  },
  {
    "id": "chap8-ck1#19",
    "quest": [
      "T-Shirt"
    ],
    "answer": [
      "футб_о_лка T-Shirt"
    ]
  },
  {
    "id": "chap8-ck1#20",
    "quest": [
      "~Pl.~ Jeans"
    ],
    "answer": [
      "дж_и_нсы"
    ]
  },
  {
    "id": "chap8-ck1#21",
    "quest": [
      "Hemd"
    ],
    "answer": [
      "руб_а_шка"
    ]
  },
  {
    "id": "chap8-ck1#22",
    "quest": [
      "Bluse"
    ],
    "answer": [
      "бл_у_зка"
    ]
  },
  {
    "id": "chap8-ck1#23",
    "quest": [
      "Rock"
    ],
    "answer": [
      "_ю_бка"
    ]
  },
  {
    "id": "chap8-ck1#24",
    "quest": [
      "Mantel"
    ],
    "answer": [
      "пальт_о_"
    ]
  },
  {
    "id": "chap8-ck1#25",
    "quest": [
      "~Pl.~ (Damen-) Schuhe"
    ],
    "answer": [
      "т_у_фли"
    ]
  },
  {
    "id": "chap8-ck1#26",
    "quest": [
      "~Pl.~ Hose"
    ],
    "answer": [
      "бр_ю_ки"
    ]
  },
  {
    "id": "chap8-ck1#27",
    "quest": [
      "Kleid"
    ],
    "answer": [
      "пл_а_тье"
    ]
  },
  {
    "id": "chap8-ck1#28",
    "quest": [
      "Tasche"
    ],
    "answer": [
      "с_у_мка"
    ]
  },
  {
    "id": "chap8-ck1#29",
    "quest": [
      "~Pl.~ Schuhe",
      "Schnürschuhe"
    ],
    "answer": [
      "бот_и_нки"
    ]
  },
  {
    "id": "chap8-ck1#33",
    "quest": [
      "Frau"
    ],
    "answer": [
      "ж_е_нщина"
    ]
  },
  {
    "id": "chap8-ck1#34",
    "quest": [
      "Mann"
    ],
    "answer": [
      "мужч_и_на ~maskulinum~"
    ]
  },
  {
    "id": "chap8-ck1#30",
    "quest": [
      "Frauen-"
    ],
    "answer": [
      "женский",
      "женская",
      "женское",
      "женскые"
    ]
  },
  {
    "id": "chap8-ck1#31",
    "quest": [
      "Männer-",
      "Herren-"
    ],
    "answer": [
      "мужской",
      "мужская",
      "мужское",
      "мужские"
    ]
  },
  {
    "id": "chap8-ck1#32",
    "quest": [
      "Schuhe",
      "Schuhwerk"
    ],
    "answer": [
      "_о_бувь ~femininum~"
    ]
  }
]